post_analysis_clustering/__init__.py
post_analysis_clustering/prep_data.py
post_analysis_clustering/utils.py
post_analysis_clustering/_procedural/lean_feature.py
post_analysis_clustering/_procedural/plot_cluster_metrics.py
post_analysis_clustering/_procedural/plot_dim_reduction.py
post_analysis_clustering/_procedural/plot_overlap.py
post_analysis_clustering/_procedural/plot_profile.py
post_analysis_clustering/_procedural/plot_vis_cluster.py
post_analysis_clustering/_procedural/select_lean_feature_09062025.py
post_analysis_clustering/_procedural/test_chisquare.py
post_analysis_clustering/lean_feature/__init__.py
post_analysis_clustering/lean_feature/base.py
post_analysis_clustering/lean_feature/model_creation.py
post_analysis_clustering/lean_feature/select_feature_chisq.py
post_analysis_clustering/lean_feature/select_feature_rank.py
post_analysis_clustering/lean_feature/select_feature_thres.py
post_analysis_clustering/visualize/__init__.py
post_analysis_clustering/visualize/base.py
post_analysis_clustering/visualize/vis_cluster.py
post_analysis_clustering/visualize/vis_dim_reduction.py
post_analysis_clustering/visualize/vis_overlap.py
post_analysis_clustering/visualize/vis_perf.py
post_analysis_clustering/visualize/vis_profile.py
post_analysis_clustering-0.1.6.dist-info/licenses/LICENSE
post_analysis_clustering-0.1.6.dist-info/METADATA
post_analysis_clustering-0.1.6.dist-info/WHEEL
post_analysis_clustering-0.1.6.dist-info/top_level.txt
post_analysis_clustering-0.1.6.dist-info/RECORD
